spectroscopy_data-0.15.dist-info/RECORD
spectroscopy_data-0.15.dist-info/DESCRIPTION.rst
spectroscopy_data-0.15.dist-info/top_level.txt
spectroscopy_data-0.15.dist-info/WHEEL
spectroscopy_data-0.15.dist-info/metadata.json
spectroscopy_data-0.15.dist-info/METADATA
spectroscopy_data/__init__.py
spectroscopy_data/utils.py
spectroscopy_data/visualization.py
spectroscopy_data/reduction.py
spectroscopy_data/pretreatment.py
