Metadata-Version: 2.0
Name: spectroscopy-data
Version: 0.15
Summary: Provides data to go along with spectroscopy.ramer.at
Home-page: https://github.com/GeorgRamer/spectroscopy_data
Author: Georg Ramer
Author-email: georg.ramer@gmail.com
License: UNKNOWN
Download-URL: https://github.com/GeorgRamer/spectroscopy_data/archive/0.15.tar.gz
Platform: UNKNOWN
Classifier: Development Status :: 4 - Beta
Classifier: Topic :: Scientific/Engineering
Classifier: Intended Audience :: Science/Research
Classifier: Intended Audience :: Education
Classifier: Programming Language :: Python :: 3
Requires-Python: >=3.6
Requires-Dist: numpy
Requires-Dist: scipy
